setup.py
Semantic_URL.egg-info/PKG-INFO
Semantic_URL.egg-info/SOURCES.txt
Semantic_URL.egg-info/dependency_links.txt
Semantic_URL.egg-info/top_level.txt
semantic_url/__init__.py
semantic_url.egg-info/SOURCES.txt