Metadata-Version: 1.1
Name: semantic-url
Version: 1.0.11
Summary: Semantic URL - A Parsing & Manipulation library for creating & using Semantic URLs
Home-page: https://github.com/bschollnick/Semantic_URL/tree/master
Author: Benjamin Schollnick
Author-email: Benjamin@schollnick.net
License: UNKNOWN
Download-URL: https://github.com/bschollnick/Semantic_URL/tree/master
Keywords: semantic,URL
Platform: UNKNOWN
Classifier: Development Status :: 5 - Production/Stable
Classifier: Intended Audience :: Developers
Classifier: Operating System :: MacOS :: MacOS X
Classifier: Operating System :: Microsoft :: Windows :: Windows 7
Classifier: Operating System :: Microsoft :: Windows :: Windows XP
Classifier: Operating System :: POSIX :: Linux
Classifier: Programming Language :: Python :: 2
